flask_useful/__init__.py
flask_useful/alembic.py
flask_useful/app.py
flask_useful/blueprints.py
flask_useful/cli.py
flask_useful/confirmation_token.py
flask_useful/decorators.py
flask_useful/flask_access.py
flask_useful/mail.py
flask_useful/py.typed
flask_useful/utils.py
flask_useful/views.py
flask_useful/sqla/__init__.py
flask_useful/sqla/confirmation_token.py
flask_useful/sqla/ma.py
flask_useful/sqla/session.py
flask_useful/sqla/utils.py
flask_useful/wtforms/__init__.py
flask_useful/wtforms/fields.py
flask_useful/wtforms/filters.py
flask_useful/wtforms/validators.py
flask_useful/wtforms/widgets.py
flask_useful-0.2.9.dist-info/LICENSE
flask_useful-0.2.9.dist-info/METADATA
flask_useful-0.2.9.dist-info/WHEEL
flask_useful-0.2.9.dist-info/top_level.txt
flask_useful-0.2.9.dist-info/RECORD
