Metadata-Version: 2.1
Name: flask-useful
Version: 0.2.9
Summary: A set of useful tools for the Flask microframework.
Author-email: Kirill Vercetti <office@kyzima-spb.com>
License: MIT License
Project-URL: Homepage, https://github.com/kyzima-spb/flask-useful
Project-URL: Repository, https://github.com/kyzima-spb/flask-useful.git
Classifier: Environment :: Web Environment
Classifier: Intended Audience :: Developers
Classifier: Operating System :: OS Independent
Classifier: Programming Language :: Python
Classifier: Framework :: Flask
Classifier: Development Status :: 3 - Alpha
Classifier: Topic :: Internet :: WWW/HTTP
Classifier: Topic :: Internet :: WWW/HTTP :: Dynamic Content
Requires-Python: >=3.7
License-File: LICENSE
Requires-Dist: Flask >=1.0
Requires-Dist: typing-extensions ; python_version < "3.9"
Provides-Extra: dev
Requires-Dist: mypy ; extra == 'dev'
Provides-Extra: sqla
Requires-Dist: Flask-SQLAlchemy >=2.0 ; extra == 'sqla'
Provides-Extra: wtforms
Requires-Dist: Flask-WTF >=1.0 ; extra == 'wtforms'
